kahi_minciencias_opendata_patents/Kahi_minciencias_opendata_patents.py
kahi_minciencias_opendata_patents/__init__.py
kahi_minciencias_opendata_patents/_version.py
kahi_minciencias_opendata_patents/parser.py
kahi_minciencias_opendata_patents/process_one.py
Kahi_minciencias_opendata_patents-0.1.0b0.dist-info/METADATA
Kahi_minciencias_opendata_patents-0.1.0b0.dist-info/WHEEL
Kahi_minciencias_opendata_patents-0.1.0b0.dist-info/top_level.txt
Kahi_minciencias_opendata_patents-0.1.0b0.dist-info/RECORD
